{
	"name": "CC_DataFactoryInsertOrUpdateScoreValueProcessDat_copy2",
	"properties": {
		"activities": [
			{
				"name": "Lookup File dat",
				"type": "Lookup",
				"dependsOn": [],
				"policy": {
					"timeout": "7.00:00:00",
					"retry": 0,
					"retryIntervalInSeconds": 30,
					"secureOutput": false,
					"secureInput": false
				},
				"userProperties": [],
				"typeProperties": {
					"source": {
						"type": "DelimitedTextSource",
						"storeSettings": {
							"type": "FileServerReadSettings",
							"recursive": true,
							"enablePartitionDiscovery": false
						},
						"formatSettings": {
							"type": "DelimitedTextReadSettings"
						}
					},
					"dataset": {
						"referenceName": "CCLocalFileMasterNotSplit",
						"type": "DatasetReference",
						"parameters": {
							"filePath": {
								"value": "@pipeline().parameters.inputPath",
								"type": "Expression"
							},
							"fileName": {
								"value": "@pipeline().parameters.fileDatName",
								"type": "Expression"
							}
						}
					},
					"firstRowOnly": false
				}
			},
			{
				"name": "Filter Start With 02",
				"type": "Filter",
				"dependsOn": [
					{
						"activity": "Lookup File dat",
						"dependencyConditions": [
							"Succeeded"
						]
					}
				],
				"userProperties": [],
				"typeProperties": {
					"items": {
						"value": "@activity('Lookup File dat').output.value",
						"type": "Expression"
					},
					"condition": {
						"value": "@startswith(item().Prop_0,'02')",
						"type": "Expression"
					}
				}
			},
			{
				"name": "ForEach row",
				"type": "ForEach",
				"dependsOn": [
					{
						"activity": "Filter Start With 02",
						"dependencyConditions": [
							"Succeeded"
						]
					}
				],
				"userProperties": [],
				"typeProperties": {
					"items": {
						"value": "@activity('Filter Start With 02').output.Value",
						"type": "Expression"
					},
					"batchCount": 20,
					"activities": [
						{
							"name": "Script Insert Table CC_DATA_FACTORY_HIST",
							"type": "Script",
							"dependsOn": [
								{
									"activity": "Insert or update scoreValue",
									"dependencyConditions": [
										"Failed"
									]
								}
							],
							"policy": {
								"timeout": "7.00:00:00",
								"retry": 0,
								"retryIntervalInSeconds": 30,
								"secureOutput": false,
								"secureInput": false
							},
							"userProperties": [],
							"linkedServiceName": {
								"referenceName": "AzureSqlDatabase1",
								"type": "LinkedServiceReference"
							},
							"typeProperties": {
								"scripts": [
									{
										"type": "Query",
										"text": {
											"value": "@concat('INSERT INTO ',pipeline().parameters.SCHEMA,'.CC_DATA_FACTORY_HIST \n    (CREATED,\n\tCREATED_BY,\n\tLAST_UPD,\n\tLAST_UPD_BY,\n\tDATA_ID,\n\tDESCRIPTION,\n\tERROR_MSG,\n\tSTATUS) VALUES (CONVERT(DATETIME2(0),'''\n\t,convertTimeZone(utcNow(),'UTC','SE Asia Standard Time'),'''),\n\t''',pipeline().parameters.CREDIT_USER,''',CONVERT(DATETIME2(0),'''\n\t,convertTimeZone(utcNow(),'UTC','SE Asia Standard Time'),'''),\n\t''',pipeline().parameters.CREDIT_USER,''',\n\t',pipeline().parameters.dataId,',\n\t''',item().Prop_0,''',\n\t''',substring(replace(activity('Insert or update scoreValue').Error.Message,'''','\"'),0,499),''',\n\t''E''\n\t)')",
											"type": "Expression"
										}
									}
								]
							}
						},
						{
							"name": "Insert or update scoreValue",
							"type": "ExecutePipeline",
							"dependsOn": [],
							"userProperties": [],
							"typeProperties": {
								"pipeline": {
									"referenceName": "CC_InsertOrUpdateScoreValueCheckClLevel_copy1",
									"type": "PipelineReference"
								},
								"waitOnCompletion": true,
								"parameters": {
									"line": {
										"value": "@item().Prop_0",
										"type": "Expression"
									},
									"SCHEMA": {
										"value": "@pipeline().parameters.SCHEMA",
										"type": "Expression"
									},
									"CREDIT_USER": {
										"value": "@pipeline().parameters.CREDIT_USER",
										"type": "Expression"
									},
									"dataId": {
										"value": "@pipeline().parameters.dataId",
										"type": "Expression"
									}
								}
							}
						}
					]
				}
			},
			{
				"name": "Update CC_DATA_FACTORY Catch Loop Insert HIST",
				"description": "",
				"type": "Script",
				"dependsOn": [
					{
						"activity": "ForEach row",
						"dependencyConditions": [
							"Failed"
						]
					}
				],
				"policy": {
					"timeout": "7.00:00:00",
					"retry": 0,
					"retryIntervalInSeconds": 30,
					"secureOutput": false,
					"secureInput": false
				},
				"userProperties": [],
				"linkedServiceName": {
					"referenceName": "AzureSqlDatabase1",
					"type": "LinkedServiceReference"
				},
				"typeProperties": {
					"scripts": [
						{
							"type": "Query",
							"text": {
								"value": "@concat('UPDATE ',pipeline().parameters.SCHEMA,'.CC_DATA_FACTORY\n    SET LAST_UPD = CONVERT(DATETIME2(0),'''\n\t,convertTimeZone(utcNow(),'UTC','SE Asia Standard Time'),'''),\n\tLAST_UPD_BY =''',pipeline().parameters.CREDIT_USER,''',\n\tSTATUS = ''E'',\n\tFILE_NAME = ''',pipeline().parameters.fileDatName,''',\n\tDESCRIPTION = ''Process file name : ',pipeline().parameters.fileDatName,' total count ',string(activity('Lookup File dat').output.count),' record -> count process ',string(length(activity('Filter Start With 02').output.Value)),' record.''\n\tWHERE DATA_ID = ',pipeline().parameters.dataId)",
								"type": "Expression"
							}
						}
					]
				}
			},
			{
				"name": "If have Error Record",
				"type": "IfCondition",
				"dependsOn": [
					{
						"activity": "ForEach row",
						"dependencyConditions": [
							"Succeeded"
						]
					}
				],
				"userProperties": [],
				"typeProperties": {
					"expression": {
						"value": "@empty(concat('SELECT TOP(1) ''Y'' FROM ',pipeline().parameters.SCHEMA,'.CC_DATA_FACTORY_HIST WHERE DATA_ID = ''',pipeline().parameters.dataId,''' AND STATUS = ''E'''))\n",
						"type": "Expression"
					},
					"ifFalseActivities": [
						{
							"name": "Update CC_DATA_FACTORY Success",
							"description": "",
							"type": "Script",
							"dependsOn": [],
							"policy": {
								"timeout": "7.00:00:00",
								"retry": 0,
								"retryIntervalInSeconds": 30,
								"secureOutput": false,
								"secureInput": false
							},
							"userProperties": [],
							"linkedServiceName": {
								"referenceName": "AzureSqlDatabase1",
								"type": "LinkedServiceReference"
							},
							"typeProperties": {
								"scripts": [
									{
										"type": "Query",
										"text": {
											"value": "@concat('UPDATE ',pipeline().parameters.SCHEMA,'.CC_DATA_FACTORY\n    SET LAST_UPD = CONVERT(DATETIME2(0),'''\n\t,convertTimeZone(utcNow(),'UTC','SE Asia Standard Time'),'''),\n\tLAST_UPD_BY =''',pipeline().parameters.CREDIT_USER,''',\n\tSTATUS = ''S'',\n\tFILE_NAME = ''',pipeline().parameters.fileDatName,''',\n\tDESCRIPTION = ''Process file name : ',pipeline().parameters.fileDatName,' total count ',string(activity('Lookup File dat').output.count),' record -> count process ',string(length(activity('Filter Start With 02').output.Value)),' record.''\n\tWHERE DATA_ID = ',pipeline().parameters.dataId)",
											"type": "Expression"
										}
									}
								]
							}
						}
					],
					"ifTrueActivities": [
						{
							"name": "Update CC_DATA_FACTORY haveErrorRow is true",
							"description": "",
							"type": "Script",
							"dependsOn": [],
							"policy": {
								"timeout": "7.00:00:00",
								"retry": 0,
								"retryIntervalInSeconds": 30,
								"secureOutput": false,
								"secureInput": false
							},
							"userProperties": [],
							"linkedServiceName": {
								"referenceName": "AzureSqlDatabase1",
								"type": "LinkedServiceReference"
							},
							"typeProperties": {
								"scripts": [
									{
										"type": "Query",
										"text": {
											"value": "@concat('UPDATE ',pipeline().parameters.SCHEMA,'.CC_DATA_FACTORY\n    SET LAST_UPD = CONVERT(DATETIME2(0),'''\n\t,convertTimeZone(utcNow(),'UTC','SE Asia Standard Time'),'''),\n\tLAST_UPD_BY =''',pipeline().parameters.CREDIT_USER,''',\n\tSTATUS = ''E'',\n\tFILE_NAME = ''',pipeline().parameters.fileDatName,''',\n\tDESCRIPTION = ''Process file name : ',pipeline().parameters.fileDatName,' total count ',string(activity('Lookup File dat').output.count),' record -> count process ',string(length(activity('Filter Start With 02').output.Value)),' record.''\n\tWHERE DATA_ID = ',pipeline().parameters.dataId)",
											"type": "Expression"
										}
									}
								]
							}
						}
					]
				}
			},
			{
				"name": "Move FIle Sync",
				"type": "ExecutePipeline",
				"dependsOn": [
					{
						"activity": "If have Error Record",
						"dependencyConditions": [
							"Succeeded"
						]
					}
				],
				"userProperties": [],
				"typeProperties": {
					"pipeline": {
						"referenceName": "CC_MoveFile",
						"type": "PipelineReference"
					},
					"waitOnCompletion": true,
					"parameters": {
						"inDir": {
							"value": "@pipeline().parameters.inputPath",
							"type": "Expression"
						},
						"outDir": {
							"value": "@pipeline().parameters.moveInputPath",
							"type": "Expression"
						},
						"inName": {
							"value": "@pipeline().parameters.fileSyncName",
							"type": "Expression"
						},
						"outName": {
							"value": "@pipeline().parameters.fileSyncName",
							"type": "Expression"
						}
					}
				}
			},
			{
				"name": "Move FIle Dat",
				"type": "ExecutePipeline",
				"dependsOn": [
					{
						"activity": "If have Error Record",
						"dependencyConditions": [
							"Succeeded"
						]
					}
				],
				"userProperties": [],
				"typeProperties": {
					"pipeline": {
						"referenceName": "CC_MoveFile",
						"type": "PipelineReference"
					},
					"waitOnCompletion": true,
					"parameters": {
						"inDir": {
							"value": "@pipeline().parameters.inputPath",
							"type": "Expression"
						},
						"outDir": {
							"value": "@pipeline().parameters.moveInputPath",
							"type": "Expression"
						},
						"inName": {
							"value": "@pipeline().parameters.fileDatName",
							"type": "Expression"
						},
						"outName": {
							"value": "@pipeline().parameters.fileDatName",
							"type": "Expression"
						}
					}
				}
			},
			{
				"name": "update data facEnd Process Move file sync Error",
				"type": "Script",
				"dependsOn": [
					{
						"activity": "Move FIle Sync",
						"dependencyConditions": [
							"Failed"
						]
					}
				],
				"policy": {
					"timeout": "7.00:00:00",
					"retry": 0,
					"retryIntervalInSeconds": 30,
					"secureOutput": false,
					"secureInput": false
				},
				"userProperties": [],
				"linkedServiceName": {
					"referenceName": "AzureSqlDatabase1",
					"type": "LinkedServiceReference"
				},
				"typeProperties": {
					"scripts": [
						{
							"type": "Query",
							"text": {
								"value": "@concat('UPDATE ',pipeline().parameters.SCHEMA,'.CC_DATA_FACTORY \n\tSET LAST_UPD = CONVERT(DATETIME2(0),'''\n\t,convertTimeZone(utcNow(),'UTC','SE Asia Standard Time'),''')\n\t, LAST_UPD_BY = ''',\n\tpipeline().parameters.CREDIT_USER,\n\t''', STATUS = ''E'',',\n\t' DESCRIPTION = ''Unable to move the file name : ',pipeline().parameters.fileSyncName,'''',\n\t' WHERE DATA_ID =',pipeline().parameters.dataId,';')",
								"type": "Expression"
							}
						}
					]
				}
			},
			{
				"name": "update data fac End Process Move file dat Error",
				"type": "Script",
				"dependsOn": [
					{
						"activity": "Move FIle Dat",
						"dependencyConditions": [
							"Failed"
						]
					}
				],
				"policy": {
					"timeout": "7.00:00:00",
					"retry": 0,
					"retryIntervalInSeconds": 30,
					"secureOutput": false,
					"secureInput": false
				},
				"userProperties": [],
				"linkedServiceName": {
					"referenceName": "AzureSqlDatabase1",
					"type": "LinkedServiceReference"
				},
				"typeProperties": {
					"scripts": [
						{
							"type": "Query",
							"text": {
								"value": "@concat('UPDATE ',pipeline().parameters.SCHEMA,'.CC_DATA_FACTORY \n\tSET LAST_UPD = CONVERT(DATETIME2(0),'''\n\t,convertTimeZone(utcNow(),'UTC','SE Asia Standard Time'),''')\n\t, LAST_UPD_BY = ''',\n\tpipeline().parameters.CREDIT_USER,\n\t''', STATUS = ''E'',',\n\t' DESCRIPTION = ''Unable to move the file name : ',pipeline().parameters.fileSyncName,'''',\n\t' WHERE DATA_ID =',pipeline().parameters.dataId,';')",
								"type": "Expression"
							}
						}
					]
				}
			}
		],
		"parameters": {
			"SCHEMA": {
				"type": "string"
			},
			"DATA_TYPE": {
				"type": "string"
			},
			"CREDIT_USER": {
				"type": "string"
			},
			"inputPath": {
				"type": "string"
			},
			"moveInputPath": {
				"type": "string"
			},
			"fileDatName": {
				"type": "string"
			},
			"dataId": {
				"type": "string"
			},
			"fileSyncName": {
				"type": "string"
			}
		},
		"variables": {
			"haveErrorRow": {
				"type": "Boolean",
				"defaultValue": false
			}
		},
		"annotations": []
	}
}